MANIFEST.in
README.rst
setup.py
cmsplugin_filer_gallery/__init__.py
cmsplugin_filer_gallery/cms_app.py
cmsplugin_filer_gallery/cms_plugins.py
cmsplugin_filer_gallery/models.py
cmsplugin_filer_gallery.egg-info/PKG-INFO
cmsplugin_filer_gallery.egg-info/SOURCES.txt
cmsplugin_filer_gallery.egg-info/dependency_links.txt
cmsplugin_filer_gallery.egg-info/not-zip-safe
cmsplugin_filer_gallery.egg-info/requires.txt
cmsplugin_filer_gallery.egg-info/top_level.txt
cmsplugin_filer_gallery/locale/en/LC_MESSAGES/django.po
cmsplugin_filer_gallery/locale/en/LC_MESSAGES/djangojs.po
cmsplugin_filer_gallery/static/cmsplugin_filer_gallery/cmsplugin_filer_gallery.css
cmsplugin_filer_gallery/templates/cmsplugin_filer_gallery/gallery.html
cmsplugin_filer_gallery/test/__init__.py
cmsplugin_filer_gallery/test/run_tests.py
cmsplugin_filer_gallery/test/testapp/__init__.py
cmsplugin_filer_gallery/test/testapp/models.py
cmsplugin_filer_gallery/test/testapp/urls.py