Metadata-Version: 1.0
Name: cmsplugin-filer-gallery
Version: 1.0.1.pre-alpha
Summary: Django CMS plugin for django-filer-gallery
Home-page: http://github.com/fivethreeo/cmsplugin-filer-gallery.git
Author: Oyvind Saltvik
Author-email: oyvind.saltvik@gmail.com
License: UNKNOWN
Platform: UNKNOWN
Classifier: Development Status :: 4 - Beta
Classifier: Environment :: Web Environment
Classifier: Intended Audience :: Developers
Classifier: License :: OSI Approved :: BSD License
Classifier: Operating System :: OS Independent
Classifier: Programming Language :: Python
Classifier: Framework :: Django
